liveai/__init__.py
liveai/version.py
liveai/agents/__init__.py
liveai/agents/_exceptions.py
liveai/agents/inference_runner.py
liveai/agents/job.py
liveai/agents/jupyter.py
liveai/agents/log.py
liveai/agents/plugin.py
liveai/agents/py.typed
liveai/agents/types.py
liveai/agents/vad.py
liveai/agents/version.py
liveai/agents/worker.py
liveai/agents/beta/__init__.py
liveai/agents/beta/workflows/__init__.py
liveai/agents/beta/workflows/email_address.py
liveai/agents/cli/__init__.py
liveai/agents/cli/_run.py
liveai/agents/cli/cli.py
liveai/agents/cli/log.py
liveai/agents/cli/proto.py
liveai/agents/cli/watcher.py
liveai/agents/inference/__init__.py
liveai/agents/inference/_utils.py
liveai/agents/inference/llm.py
liveai/agents/inference/stt.py
liveai/agents/inference/tts.py
liveai/agents/ipc/__init__.py
liveai/agents/ipc/channel.py
liveai/agents/ipc/inference_executor.py
liveai/agents/ipc/inference_proc_executor.py
liveai/agents/ipc/inference_proc_lazy_main.py
liveai/agents/ipc/job_executor.py
liveai/agents/ipc/job_proc_executor.py
liveai/agents/ipc/job_proc_lazy_main.py
liveai/agents/ipc/job_thread_executor.py
liveai/agents/ipc/log_queue.py
liveai/agents/ipc/mock_room.py
liveai/agents/ipc/proc_client.py
liveai/agents/ipc/proc_pool.py
liveai/agents/ipc/proto.py
liveai/agents/ipc/supervised_proc.py
liveai/agents/llm/__init__.py
liveai/agents/llm/_strict.py
liveai/agents/llm/chat_context.py
liveai/agents/llm/fallback_adapter.py
liveai/agents/llm/llm.py
liveai/agents/llm/mcp.py
liveai/agents/llm/realtime.py
liveai/agents/llm/remote_chat_context.py
liveai/agents/llm/tool_context.py
liveai/agents/llm/utils.py
liveai/agents/llm/_provider_format/__init__.py
liveai/agents/llm/_provider_format/anthropic.py
liveai/agents/llm/_provider_format/aws.py
liveai/agents/llm/_provider_format/google.py
liveai/agents/llm/_provider_format/mistralai.py
liveai/agents/llm/_provider_format/openai.py
liveai/agents/llm/_provider_format/utils.py
liveai/agents/metrics/__init__.py
liveai-1.1.0.dist-info/licenses/LICENSE
liveai-1.1.0.dist-info/METADATA
liveai-1.1.0.dist-info/WHEEL
liveai-1.1.0.dist-info/top_level.txt
liveai-1.1.0.dist-info/RECORD
