Metadata-Version: 2.4
Name: liveai
Version: 1.1.0
Summary: LiveAI realtime voice SDK
Author-email: LiveAI <support@liveai.io>
License: Apache-2.0
Project-URL: Homepage, https://liveai.io
Project-URL: Documentation, https://docs.liveai.io
Project-URL: Source, https://git.liveai.io/liveai
Keywords: liveai,webrtc,realtime,audio,video,agents
Classifier: Programming Language :: Python :: 3
Classifier: Programming Language :: Python :: 3 :: Only
Classifier: Programming Language :: Python :: 3.9
Classifier: Programming Language :: Python :: 3.10
Classifier: Programming Language :: Python :: 3.11
Classifier: Programming Language :: Python :: 3.12
Classifier: Programming Language :: Python :: 3.13
Classifier: Intended Audience :: Developers
Classifier: License :: OSI Approved :: Apache Software License
Classifier: Topic :: Multimedia :: Sound/Audio
Classifier: Topic :: Multimedia :: Video
Classifier: Topic :: Scientific/Engineering :: Artificial Intelligence
Requires-Python: >=3.9
License-File: LICENSE
Requires-Dist: aiohttp>=3.9
Requires-Dist: aiofiles>=24
Requires-Dist: av<16,>=14
Requires-Dist: certifi>=2025.6.15
Requires-Dist: click>=8.1
Requires-Dist: colorama>=0.4.6
Requires-Dist: docstring-parser>=0.16
Requires-Dist: eval-type-backport
Requires-Dist: nest-asyncio>=1.6.0
Requires-Dist: numpy>=1.26
Requires-Dist: openai>=1.99.2
Requires-Dist: opentelemetry-api>=1.34
Requires-Dist: opentelemetry-exporter-otlp>=1.34.1
Requires-Dist: opentelemetry-sdk>=1.34.1
Requires-Dist: prometheus-client>=0.22
Requires-Dist: protobuf>=4.25
Requires-Dist: psutil>=7.0
Requires-Dist: pydantic<3,>=2
Requires-Dist: pyjwt>=2.0
Requires-Dist: sounddevice>=0.5
Requires-Dist: types-protobuf>=4
Requires-Dist: typing-extensions>=4.12
Requires-Dist: watchfiles>=1.0
Requires-Dist: livekit-blingfire>=1.0
Provides-Extra: codecs
Requires-Dist: av>=12.0.0; extra == "codecs"
Requires-Dist: numpy>=1.26; extra == "codecs"
Provides-Extra: images
Requires-Dist: pillow>=10.3.0; extra == "images"
Provides-Extra: openai
Requires-Dist: openai[realtime]>=1.107.2; extra == "openai"
Dynamic: license-file
